mlhandmade/__init__.py
mlhandmade/plot.py
mlhandmade/test.py
mlhandmade/base/__init__.py
mlhandmade/base/base.py
mlhandmade/discriminant_analysis/__init__.py
mlhandmade/discriminant_analysis/lda.py
mlhandmade/discriminant_analysis/qda.py
mlhandmade/kernel_methods/__init__.py
mlhandmade/kernel_methods/kernel.py
mlhandmade/kernel_methods/kernel_ridge.py
mlhandmade/kernel_methods/linear.py
mlhandmade/kernel_methods/poly.py
mlhandmade/kernel_methods/rbf.py
mlhandmade/kernel_methods/svm.py
mlhandmade/knn/__init__.py
mlhandmade/knn/knn.py
mlhandmade/knn/ball_tree/__init__.py
mlhandmade/knn/ball_tree/ball_tree.py
mlhandmade/knn/ball_tree/base.py
mlhandmade/knn/kd_tree/__init__.py
mlhandmade/knn/kd_tree/base.py
mlhandmade/knn/kd_tree/kd_tree.py
mlhandmade/linear_models/__init__.py
mlhandmade/linear_models/linear_classifier.py
mlhandmade/linear_models/linear_regressor.py
mlhandmade/linear_models/losses.py
mlhandmade/linear_models/optimizers.py
mlhandmade/model_selection/__init__.py
mlhandmade/model_selection/class_metrics.py
mlhandmade/model_selection/kflod_cv.py
mlhandmade/multiclass/__init__.py
mlhandmade/multiclass/multiclass.py
mlhandmade/preprocessing/__init__.py
mlhandmade/preprocessing/data_preprocessiong.py
mlhandmade/svm/__init__.py
mlhandmade/svm/kernel.py
mlhandmade/svm/linear.py
mlhandmade/svm/poly.py
mlhandmade/svm/rbf.py
mlhandmade/svm/svc.py
mlhandmade/svm/svm.py
mlhandmade/tree/__init__.py
mlhandmade/tree/criterion.py
mlhandmade/tree/splitter.py
mlhandmade/tree/tree.py
mlhandmade/utils/__init__.py
mlhandmade/utils/plot.py
mlhandmade/utils/validations.py
mlhandmade-0.0.8.dist-info/METADATA
mlhandmade-0.0.8.dist-info/WHEEL
mlhandmade-0.0.8.dist-info/top_level.txt
mlhandmade-0.0.8.dist-info/RECORD
