Metadata-Version: 2.1
Name: mlhandmade
Version: 0.0.8
Summary: Implemented some ML routines
Author: gittasche
Requires-Dist: numpy
Requires-Dist: matplotlib
